funcprofiler/__init__.py
funcprofiler-1.1.0.dist-info/licenses/LICENSE
funcprofiler-1.1.0.dist-info/METADATA
funcprofiler-1.1.0.dist-info/WHEEL
funcprofiler-1.1.0.dist-info/top_level.txt
funcprofiler-1.1.0.dist-info/RECORD
